klasifikasi/__init__.py
klasifikasi/_klasifikasi_model.py
klasifikasi/_settings.py
klasifikasi/klasifikasi.py
klasifikasi_py-0.0.2.dist-info/METADATA
klasifikasi_py-0.0.2.dist-info/WHEEL
klasifikasi_py-0.0.2.dist-info/top_level.txt
klasifikasi_py-0.0.2.dist-info/RECORD
