Metadata-Version: 2.1
Name: klasifikasi-py
Version: 0.0.2
Summary: Official Klasifikasi (https://klasifikasi.com) API Client Library
Home-page: https://github.com/bahasa-ai/klasifikasi-py
Author: Z. E. Sagata
Author-email: saga@bahasa.ai
License: UNKNOWN
Platform: UNKNOWN
Classifier: Programming Language :: Python :: 3
Classifier: License :: OSI Approved :: MIT License
Classifier: Operating System :: OS Independent
Requires-Python: >=3.7
Requires-Dist: arrow (==0.17.0)
Requires-Dist: bleach (==3.2.1)
Requires-Dist: certifi (==2020.11.8)
Requires-Dist: chardet (==3.0.4)
Requires-Dist: colorama (==0.4.4)
Requires-Dist: docutils (==0.16)
Requires-Dist: idna (==2.10)
Requires-Dist: importlib-metadata (==3.1.0)
Requires-Dist: keyring (==21.5.0)
Requires-Dist: packaging (==20.7)
Requires-Dist: pkginfo (==1.6.1)
Requires-Dist: Pygments (==2.7.2)
Requires-Dist: pyparsing (==2.4.7)
Requires-Dist: python-dateutil (==2.8.1)
Requires-Dist: pywin32-ctypes (==0.2.0)
Requires-Dist: readme-renderer (==28.0)
Requires-Dist: requests (==2.25.0)
Requires-Dist: requests-toolbelt (==0.9.1)
Requires-Dist: rfc3986 (==1.4.0)
Requires-Dist: six (==1.15.0)
Requires-Dist: tqdm (==4.54.0)
Requires-Dist: twine (==3.2.0)
Requires-Dist: urllib3 (==1.26.2)
Requires-Dist: webencodings (==0.5.1)
Requires-Dist: wincertstore (==0.2)
Requires-Dist: zipp (==3.4.0)
